sage_explorer/__init__.py
sage_explorer/_catalogs.py
sage_explorer/_sage_catalog.py
sage_explorer/_widgets.py
sage_explorer/explored_member.py
sage_explorer/flatsurf.yml
sage_explorer/properties.yml
sage_explorer/sage_explorer.py
sage_explorer-0.5.3.dist-info/LICENSE
sage_explorer-0.5.3.dist-info/METADATA
sage_explorer-0.5.3.dist-info/WHEEL
sage_explorer-0.5.3.dist-info/top_level.txt
sage_explorer-0.5.3.dist-info/RECORD
