Metadata-Version: 2.1
Name: sage-explorer
Version: 0.5.3
Summary: Jupyter explorer widget for SAGE objects
Home-page: https://github.com/sagemath/sage-explorer
Author: Odile Bénassy, Nicolas M. Thiéry
Author-email: odile.benassy@u-psud.fr
License: GPLv2+
Keywords: SageMath widget explorer jupyter notebook
Platform: UNKNOWN
Classifier: Development Status :: 3 - Alpha
Classifier: Intended Audience :: Science/Research
Classifier: Topic :: Scientific/Engineering :: Mathematics
Classifier: License :: OSI Approved :: GNU General Public License v2 or later (GPLv2+)
Classifier: Programming Language :: Python :: 3
Classifier: Programming Language :: Python :: 3.6
Classifier: Programming Language :: Python :: 3.7
Classifier: Framework :: Jupyter
Requires-Dist: PyYAML
Requires-Dist: cysignals
Requires-Dist: ipyevents
Requires-Dist: ipywidgets (>=7.5.0)
Requires-Dist: sage-combinat-widgets
